{
  "name": "Belt-Fed Magazine",
  "description": "Your weapon gains a <span class=\"highlight\">much larger magazine that </span><span class=\"isNegative\">requires spin-up time</span>, starting with a <span class=\"highlight\">slower initial fire rate and becoming faster over the spin-up time</span>.",
  "cost": "6300",
  "tier": "4",
  "activation": "Passive",
  "slot": "Weapon",
  "image": "upgrades/mods_weapon/auto_reloader_psd",
  "components": null,
  "componentsOf": [],
  "target_types": null,
  "shop_filters": [
    "EShopFilterFireRate",
    "EShopFilterClipSize"
  ],
  "tooltip": {
    "Default": [
      {
        "ability_properties": {
          "spin_up_time": {
            "value": 3,
            "style": null,
            "is_negative": true
          },
          "initial_fire_rate_decrease": {
            "value": 40,
            "style": null,
            "is_negative": true
          },
          "max_fire_rate_increase": {
            "value": 60,
            "style": null,
            "is_negative": false
          }
        },
        "elevated_ability_properties": {},
        "important_ability_properties": {
          "bonus_clip_size_percent": {
            "value": 125,
            "style": null,
            "is_conditional": false
          }
        },
        "description": "Your weapon gains a <span class=\"highlight\">much larger magazine that </span><span class=\"isNegative\">requires spin-up time</span>, starting with a <span class=\"highlight\">slower initial fire rate and becoming faster over the spin-up time</span>."
      }
    ]
  },
  "disabled": true,
  "ability_cooldown": 0,
  "ability_duration": 0,
  "ability_cast_range": 0,
  "ability_unit_target_limit": 1,
  "ability_cast_delay": 0,
  "ability_channel_time": 0,
  "ability_post_cast_duration": 0,
  "ability_charges": 0,
  "ability_cooldown_between_charge": 0,
  "channel_move_speed": 50,
  "ability_resource_cost": 0,
  "tech_power": 0,
  "weapon_power": 0,
  "bonus_clip_size_percent": 125,
  "spin_up_time": 3.5,
  "spin_up_decay": 1,
  "initial_fire_rate_decrease": 40,
  "max_fire_rate_increase": 60,
  "bonus_reload_time": 0
}